aio_kraken_ws/__init__.py
aio_kraken_ws/_version.py
aio_kraken_ws/kraken_ws.py
aio_kraken_ws/stream.py
aio_kraken_ws/ws.py
aio_kraken_ws-0.3.9.dist-info/LICENSE
aio_kraken_ws-0.3.9.dist-info/METADATA
aio_kraken_ws-0.3.9.dist-info/WHEEL
aio_kraken_ws-0.3.9.dist-info/top_level.txt
aio_kraken_ws-0.3.9.dist-info/RECORD
