Metadata-Version: 2.1
Name: aio-kraken-ws
Version: 0.3.9
Summary: Get ohlc from kraken web sockets.
Home-page: https://gitlab.com/cdlr75/aio-kraken-ws
Author: Constantin De La Roche
Author-email: constantin@botcrypto.io
License: UNKNOWN
Project-URL: Bug Reports, https://gitlab.com/cdlr75/aio-kraken-ws/issues
Project-URL: Funding, https://botcrypto.io
Project-URL: Source, https://gitlab.com/cdlr75/aio-kraken-ws
Keywords: sample kraken websockets
Platform: UNKNOWN
Classifier: Development Status :: 4 - Beta
Classifier: Intended Audience :: Developers
Classifier: Topic :: Software Development :: Build Tools
Classifier: License :: OSI Approved :: MIT License
Classifier: Programming Language :: Python :: 3.8
Requires-Python: >=3
License-File: LICENSE
Requires-Dist: websockets (==8.0.2)
Provides-Extra: test
Requires-Dist: asynctest (==0.13.0) ; extra == 'test'
Requires-Dist: pycodestyle (==2.5.0) ; extra == 'test'
Requires-Dist: pylint (==2.3.1) ; extra == 'test'
Requires-Dist: pytest (==5.1.2) ; extra == 'test'
Requires-Dist: pytest-cov (==2.7.1) ; extra == 'test'
Requires-Dist: pytest-xdist (==1.29.0) ; extra == 'test'
